_tilebox/grpc/__init__.py
_tilebox/grpc/channel.py
_tilebox/grpc/error.py
_tilebox/grpc/pagination.py
_tilebox/grpc/producer_consumer.py
_tilebox/grpc/replay.py
_tilebox/grpc/aio/__init__.py
_tilebox/grpc/aio/channel.py
_tilebox/grpc/aio/error.py
_tilebox/grpc/aio/pagination.py
_tilebox/grpc/aio/producer_consumer.py
_tilebox/grpc/aio/syncify.py
tilebox_grpc-0.48.0.dist-info/METADATA
tilebox_grpc-0.48.0.dist-info/WHEEL
tilebox_grpc-0.48.0.dist-info/RECORD
