Metadata-Version: 2.4
Name: tilebox-grpc
Version: 0.48.0
Summary: GRPC / Protocol Buffers functions for Tilebox
Project-URL: Homepage, https://tilebox.com
Project-URL: Documentation, https://docs.tilebox.com/
Author-email: "Tilebox, Inc." <support@tilebox.com>
License: MIT License
Classifier: Intended Audience :: Developers
Classifier: Intended Audience :: Science/Research
Classifier: License :: OSI Approved :: MIT License
Classifier: Operating System :: OS Independent
Classifier: Programming Language :: Python
Classifier: Programming Language :: Python :: 3
Classifier: Programming Language :: Python :: 3.10
Classifier: Programming Language :: Python :: 3.11
Classifier: Programming Language :: Python :: 3.12
Classifier: Programming Language :: Python :: 3.13
Classifier: Topic :: Scientific/Engineering
Classifier: Topic :: Software Development
Requires-Python: >=3.10
Requires-Dist: anyio>=4
Requires-Dist: grpcio-status>=1.70
Requires-Dist: grpcio>=1.70
Requires-Dist: lz4>=4
Requires-Dist: nest-asyncio>=1.5.0
Requires-Dist: protobuf>=6
